{"image_dir": "data/RVL_CDIP/images/imagesp/p/g/w/pgw58e00/2024546653.tif", "label": "15", "words": ["et", "Front", "whset", ".", "PHILIP", "HORRIS", "[", "INTER-OFFICE", "CORRESPONDENCE", "RICKHOND,", "YIRGIKIA", "Dr,", "\u00a5,", "P.", "Gannon", "Novembor", "7,", "1073", "D.", "M.", "Tong", "Plans", "and", "Objootivas", "for", "1074", "(Projoct", "1901)", "ODJECTIVE:", "To", "dovalop", "biochomical", "moans", "of", "modifying", "tobacco", "and", "tobncco", "products", "which", "will", "load", "to", "matorials", "that", "will", "bo", "both", "nccoptublo", "to", "the", "consumor", "and", "in", "addition,", "will", "elieit", "an", "altorod", "biological", "mctivity.", "INTRODUCTION:", "A", "study", "has", "boon", "centinuod", "in", "this", "projoct", "to", "obtain", "the", "background", "informution", "on", "tobacco", "procossing", "for", "bettor", "undor-", "standing", "of", "tho", "basic", "changes,", "causo", "of", "the", "changos", "and", "thoir", "significanco", "to", "thoir", "quality.", "We", "now", "havo", "the", "knowlodgo", "of", "tho", "changos", "in", "chomical", "constituonts,", "microbial", "population", "as", "well", "gs", "wume", "Of-", "the-wikjui", "unzywos", "during", "flue-curing.", "It", "is", "cvident", "fice", "our", "study", "that", "microorganisms", "do", "not", "contributo", "to", "tho", "transforma-", "tion", "of", "chomical", "constituonts", "during", "fluo-curing.", "This", "was", "shown", "by", "tho", "1ack", "of", "onzymo", "nctivitios", "in", "tho", "culturo", "modia", "as", "woll", "as", "1in", "the", "cell-freo", "oxtract", "of", "microorganiums", "grown", "in", "tobacco", "broth", "undor", "tho", "samo", "timo-tomporaturo", "profile", "as", "in", "fluo-curing.", "Although", "tho", "convorsion", "of", "some", "of", "the", "constituonts", "in", "chomical", "in", "nature", "(monsurod", "onzyme", "mctivitios", "cannot", "sccount", "for", "those", "conversions),", "tho", "most", "important", "factors", "involved", "in", "tho", "transformation", "aro", "the", "intrinsic", "plant", "onzymos.", "Tobacco", "plants,", "like", "cthor", "living", "things", "produce", "onzymos", "to", "carry", "out", "the", "complicated", "motubolic", "roactions", "%o", "sustain", "thoir", "livow.", "Diring", "the", "procossing", "of", "tobacco,", "the", "in-", "frinnic", "onzymou", "produced", "by", "tho", "lopves", "will", "eatalyzo", "tho", "convorsion", "of", "thoir", "own", "constituents", "(autolysim)", "into", "products", "which", "will", "give", "Good", "smoking", "quality.", "It", "is", "ulso", "ovidont", "from", "the", "study", "that", "tho", "onzyme", "notivitios", "change", "during", "processing", "dopending", "on", "the", "partic-", "ular", "onzyme", "ond", "curing", "conditions.", "Those", "onzymos", "can", "be", "utilizod", "for.", "moloctive:", "rerioval", "of", "tobaaco.constituonts", ":by.", "procoysing", "under", "proper", "condltions.", "-", ".", "From", "the", "information", "gathored", "during", "the", "leaf", "procosing,", "aroan", "have", "boon", "studied", "in", "an", "attompt", "to", "develop", "biochemical", "moans", "of", "modifying", "tobacco", "and_tobacco", "products", "to", "yiold", "good", "smoking", "tobacco", "with", "reducod", "biological", "activity.", "Tho", "work", "will", "be", "continued", "in", "1974,", "as", "outlined", "in", "the", "plans.", "T", "o", "T", "USA", "W", "1", "e", "i", "1", "50", "o", "i", "o", "soon", "35", "you", "Hve", "o", "urthr", "v", "o", "1."], "bbox": [[73, 238, 97, 250], [81, 268, 111, 277], [83, 293, 133, 303], [151, 298, 154, 301], [411, 143, 469, 154], [480, 142, 539, 154], [456, 158, 496, 166], [296, 169, 451, 180], [472, 167, 660, 179], [402, 193, 471, 202], [485, 193, 548, 202], [175, 249, 200, 259], [214, 248, 231, 259], [245, 248, 261, 258], [275, 248, 333, 258], [625, 244, 706, 254], [718, 243, 733, 255], [749, 243, 787, 253], [175, 275, 191, 286], [205, 275, 221, 285], [235, 275, 274, 287], [175, 302, 225, 312], [236, 301, 265, 312], [275, 301, 374, 313], [387, 300, 415, 310], [427, 299, 464, 310], [477, 299, 554, 311], [567, 297, 613, 310], [176, 356, 272, 366], [236, 383, 257, 392], [267, 382, 337, 394], [347, 380, 455, 391], [465, 382, 516, 390], [526, 379, 545, 389], [555, 378, 646, 390], [658, 378, 728, 388], [740, 377, 768, 387], [178, 396, 247, 406], [257, 395, 337, 408], [347, 394, 396, 405], [406, 393, 445, 404], [458, 393, 495, 403], [507, 393, 525, 403], [536, 392, 626, 402], [638, 391, 676, 401], [688, 390, 727, 401], [740, 390, 759, 400], [177, 409, 216, 419], [229, 408, 326, 421], [338, 408, 356, 418], [369, 407, 386, 417], [407, 408, 486, 417], [498, 406, 526, 416], [537, 405, 555, 415], [567, 405, 655, 416], [667, 404, 706, 414], [719, 403, 778, 413], [178, 425, 196, 432], [208, 421, 276, 432], [288, 420, 386, 433], [398, 420, 483, 432], [180, 448, 305, 458], [239, 474, 247, 484], [258, 473, 307, 485], [319, 473, 347, 483], [359, 473, 397, 483], [409, 471, 496, 482], [509, 471, 527, 481], [539, 470, 576, 481], [588, 470, 657, 482], [670, 470, 688, 479], [700, 469, 759, 479], [772, 469, 800, 478], [178, 487, 277, 499], [289, 486, 397, 497], [409, 487, 427, 495], [440, 485, 508, 495], [518, 484, 617, 496], [630, 483, 658, 493], [669, 483, 729, 492], [741, 482, 799, 492], [178, 500, 258, 512], [268, 499, 287, 510], [299, 500, 328, 510], [338, 499, 387, 509], [398, 499, 447, 510], [489, 499, 537, 508], [548, 497, 567, 507], [580, 497, 607, 506], [620, 496, 688, 507], [701, 495, 729, 505], [741, 495, 790, 505], [178, 513, 298, 523], [311, 513, 329, 522], [341, 512, 388, 522], [398, 511, 474, 523], [498, 510, 517, 520], [528, 512, 558, 520], [568, 509, 608, 519], [620, 509, 648, 519], [660, 508, 750, 520], [760, 507, 779, 517], [792, 507, 819, 517], [178, 528, 248, 538], [261, 526, 277, 536], [289, 525, 366, 536], [379, 524, 496, 535], [518, 522, 607, 533], [620, 521, 719, 534], [731, 523, 750, 531], [760, 520, 800, 530], [812, 523, 830, 533], [178, 542, 217, 550], [230, 539, 247, 549], [261, 539, 346, 549], [359, 539, 428, 550], [440, 537, 496, 549], [508, 535, 625, 547], [651, 535, 667, 545], [680, 534, 698, 544], [711, 534, 779, 544], [792, 533, 831, 543], [178, 555, 207, 562], [218, 552, 268, 564], [280, 552, 317, 562], [329, 550, 467, 562], [478, 549, 498, 560], [509, 550, 536, 559], [549, 548, 648, 559], [661, 548, 679, 557], [691, 547, 719, 557], [732, 546, 840, 557], [180, 566, 217, 576], [230, 565, 248, 575], [259, 564, 338, 575], [350, 564, 468, 574], [478, 562, 537, 574], [550, 561, 666, 572], [689, 560, 729, 570], [741, 561, 770, 569], [781, 559, 830, 569], [178, 579, 198, 591], [209, 579, 239, 589], [250, 578, 288, 588], [299, 577, 317, 588], [330, 579, 388, 589], [400, 576, 498, 587], [510, 576, 527, 586], [540, 575, 568, 585], [580, 574, 649, 585], [660, 573, 710, 584], [719, 567, 741, 595], [751, 572, 790, 583], [803, 574, 821, 582], [180, 592, 198, 602], [211, 592, 239, 602], [249, 591, 339, 601], [350, 590, 418, 600], [429, 589, 447, 600], [458, 588, 589, 600], [610, 589, 658, 599], [671, 587, 689, 597], [701, 587, 770, 597], [782, 585, 830, 595], [180, 605, 229, 616], [241, 605, 268, 615], [280, 606, 319, 615], [332, 604, 489, 615], [499, 602, 568, 614], [580, 603, 589, 611], [611, 601, 629, 611], [642, 600, 759, 610], [782, 599, 861, 610], [180, 619, 208, 629], [220, 618, 319, 628], [330, 617, 348, 627], [360, 619, 398, 627], [410, 616, 428, 627], [441, 616, 468, 626], [480, 615, 599, 626], [608, 614, 625, 624], [651, 613, 729, 624], [742, 613, 760, 623], [772, 613, 831, 622], [181, 631, 268, 644], [280, 632, 339, 643], [350, 629, 447, 640], [460, 629, 518, 639], [530, 628, 598, 638], [612, 627, 639, 637], [652, 627, 700, 637], [711, 625, 839, 637], [181, 645, 208, 655], [220, 645, 258, 655], [271, 644, 359, 656], [371, 643, 438, 653], [451, 642, 528, 653], [541, 641, 558, 652], [571, 641, 599, 651], [611, 639, 751, 651], [763, 641, 791, 649], [804, 639, 831, 648], [181, 658, 268, 668], [281, 657, 329, 670], [341, 659, 416, 668], [440, 656, 508, 666], [519, 655, 568, 667], [602, 654, 639, 664], [651, 654, 701, 663], [712, 653, 772, 664], [783, 652, 841, 663], [180, 672, 249, 684], [261, 673, 329, 683], [342, 671, 360, 680], [371, 672, 418, 681], [431, 670, 458, 679], [471, 669, 499, 679], [510, 667, 620, 680], [631, 666, 720, 677], [733, 665, 821, 675], [181, 686, 199, 695], [211, 684, 279, 695], [292, 684, 339, 694], [352, 683, 406, 693], [429, 682, 489, 694], [501, 682, 528, 692], [540, 680, 640, 693], [651, 680, 670, 690], [683, 680, 759, 690], [774, 679, 801, 688], [814, 679, 841, 688], [181, 698, 249, 708], [261, 699, 329, 709], [342, 696, 419, 708], [431, 696, 449, 707], [462, 696, 489, 705], [501, 695, 539, 705], [570, 694, 610, 704], [622, 693, 701, 705], [714, 693, 742, 702], [752, 692, 851, 702], [180, 711, 199, 721], [212, 711, 259, 720], [271, 712, 299, 720], [311, 709, 429, 719], [442, 707, 548, 720], [562, 707, 601, 717], [611, 706, 691, 718], [702, 705, 752, 715], [763, 705, 801, 714], [814, 705, 851, 715], [181, 724, 220, 735], [231, 723, 299, 734], [311, 722, 387, 734], [413, 721, 429, 731], [442, 721, 459, 731], [471, 720, 509, 730], [521, 720, 590, 730], [602, 719, 642, 729], [653, 719, 680, 729], [693, 718, 742, 729], [754, 718, 792, 727], [805, 718, 832, 727], [181, 738, 240, 748], [252, 735, 350, 746], [361, 735, 419, 746], [431, 734, 490, 745], [500, 732, 601, 745], [612, 731, 702, 743], [714, 733, 732, 740], [745, 731, 772, 740], [783, 730, 851, 742], [181, 749, 220, 759], [231, 750, 290, 760], [312, 747, 341, 757], [352, 747, 410, 758], [422, 746, 527, 757], [550, 745, 601, 755], [612, 746, 682, 756], [693, 746, 722, 754], [733, 743, 752, 753], [764, 742, 842, 753], [182, 762, 209, 772], [221, 761, 311, 772], [323, 760, 389, 771], [401, 760, 420, 770], [424, 758, 631, 772], [642, 758, 662, 769], [673, 756, 773, 769], [783, 756, 835, 766], [181, 777, 240, 787], [252, 774, 359, 784], [581, 772, 585, 773], [849, 771, 851, 774], [241, 800, 281, 809], [293, 799, 321, 809], [334, 798, 441, 808], [453, 797, 531, 809], [541, 796, 601, 807], [613, 796, 642, 805], [653, 795, 692, 805], [705, 794, 812, 806], [182, 815, 230, 823], [243, 812, 280, 822], [292, 812, 330, 821], [343, 811, 411, 820], [423, 810, 441, 820], [453, 812, 471, 819], [482, 810, 550, 820], [563, 810, 581, 818], [593, 808, 662, 819], [673, 807, 783, 817], [795, 809, 844, 816], [181, 825, 199, 835], [211, 825, 301, 835], [314, 824, 382, 834], [392, 823, 500, 833], [512, 822, 592, 834], [604, 822, 622, 831], [633, 820, 682, 832], [694, 820, 733, 831], [745, 819, 813, 830], [182, 838, 250, 848], [262, 837, 301, 847], [314, 836, 380, 846], [392, 835, 490, 847], [503, 834, 589, 846], [241, 863, 271, 872], [281, 862, 321, 872], [333, 861, 370, 871], [383, 861, 401, 871], [413, 860, 501, 870], [513, 860, 531, 869], [544, 859, 589, 870], [603, 861, 622, 869], [634, 858, 714, 868], [727, 858, 743, 867], [756, 858, 785, 867], [796, 857, 851, 868], [145, 910, 176, 916], [236, 910, 248, 916], [339, 897, 355, 925], [344, 905, 424, 916], [407, 897, 429, 925], [137, 919, 171, 932], [189, 921, 195, 932], [211, 922, 248, 927], [254, 922, 263, 927], [268, 920, 293, 927], [307, 920, 346, 927], [351, 920, 369, 927], [375, 909, 382, 937], [389, 922, 415, 927], [420, 922, 432, 927], [437, 922, 455, 928], [462, 921, 486, 927], [491, 922, 503, 927], [509, 920, 544, 927], [549, 922, 568, 927], [574, 921, 586, 927], [593, 922, 598, 927]]}