{"image_dir": "data/RVL_CDIP/images/imagesp/p/e/e/pee35c00/2064246310.tif", "label": "9", "words": ["THE", "NEW", "YORK", "TIMES,", "THURSDAY,", "MAY", "16,", "%", "==", "2", "Tobacco", "Giants", "Seek", "Anti-Smoking", "Laws", "By", "GLENN", "COLLING", "Seeking", "an", "altematve", "10", "Federal", "rogulacin", "of", "the", "nicocise", "i", "0haccs", "as'en", "addinive", "drug,", "two", "tobace", "ompanies", "proposed", "yesterday", "that", "Contrns", "o", "weeing", "vt", "1", "\u2018eervags", "smoking", "by", "bamning", "\u2018vending", "saies", "and", "resricting", "adver.", "daements", "and", "promotions.", "'St", "the", "companies", "ware", "raputted", "by", "Michael", "D.", "MeCurry,", "the", "Wite", "Ko", "sposman,", "whosdd", "decom.", "anies", "proposal", "\u201cfals", "e", "it", "short\u201d", "of", "o", "Presiden'scall", "10", "urb", "teenage", "smoling.", "And", "some", "antlobaccoorganaations", "dismissed", "tho", "companles\u201d", "proposl", "a8", "8", "public-", "rejations", "sunt.", "\"The", "twa", "companies", "=", "Philip", "Mor-", "Tis", "USA,", "the", "tobscco", "unit", "of", "the", "Phllp", "Merris", "Companies,", "the", "ne-.", "ton's", "largest", "elgarete", "maker,", "and", "the", "United", "Sates", "Tobacco", "Company,", "the", "nations", "Iargest", "purveyor", "of", "ing", "wbacco", "and", "snuif", "\u2014", "pro-", "and", "sporisevent", "sponsorships.", "i", "Morrs", "and", "United", "Scatss", "Tobacco", "also", "proposed", "a", "ban", "on", "the", "ot", "e", "o,", "oo", "\u2018The", "proposals", "would", "0ot", "affeet", "the", "v", "partich", "s", "spokeumas", "e", "Pl", "Mars,", "irmed", "e", "Dttt", "1nd", "uc", "g", "a0", "ne", "e", "compeies", "st", "ia", "e", "o", "for", "e", "8", "ik", "Sy", "e", "proauct", "trom", "3", "Raniares", "or", "sl", "Wi", "&", "Rieoiase", "sz", "whes", "rot", "ey", "chn", "e", "e", "218", "P", "st", "e", " baots", "corpanes", "ol", "sppEresuch", "legislasion", "only", "f", "the", "Food", "and", "Drug.", "i", "wihares", "s", "poses", "o", "epnatie", "s", "of", "o", "He", "Sk", "St", "th", "o", "et", "onces", "ey", "ol", "e", "s", "e", "he", "o", "i", "\"", "\u201cThe", "R.", "J.", "Reynolds", "Tobacco", "Com-", "ooty", "e", "Bown", "&", "Ve", "Tobacco", "Corporation,", "eaid_they", "weuld", "reserve", "comiment", "on", "yester-", "YHE", "NUMBERS", "\u2018Wherd", "Teen-Agers", "|", "Buy", "Clgaretts", "Almough", "cigaeus", "camparies", "oferedlo", "banvending", "Buy", "cigarates,", "sccaraing", "the", "Natonal", "Automatic", "Mtchandiaing", "Associaton.", "Oftha", "24.28", "bilon", "cigarete", "packs", "bougri", "i", "198\u00a2,", "about", "916", "mtion", "came", "from", "Vending", "maghines,", "scoording", "15", "Vending", "Times.", "Some", "|", "400000", "macrines", "cariod", "|", "cigaretes,", "saing", "an", "average", "f", "44", "packs", "8", "week", "each.", "]", "chairman", "of", "the", "Tobaceo", "Products", "Liablity", "Project", "at", "Norvheasiem", "\u2018nyversiy", "Schoolof", "Law", "n", "Bosion,", "\u2018nonprofit", "ancsmoking", "group.", "\u201cToey", "want", "to", "make", "sure", "that", "the", "F.DA,", "bas", "coching", "to", "do", "with", "regulating", "them.\u201d", "M.", "Parrish", "denied", "that", "the", "com-", "panies", "were", "attomptiog", "o", "avaid", "more", "stringent", "nti-iobacco", "restric-", "]", "tons.", "But", "critch", "of", "te", "wbacco", "In-", ".", "dusry", "waid", "hat", "under", "the", "compe-", "nles\u201d", "proposal,", "igarette", "brand", "im", "\u00a9", "gk", "s", "oe", "Camel", "nd", "the", "ariboro", "Ma", "would", "bo", "unattected.", "Under", "the", "Foderal", "agencys", "plan.", "\u2018mich", "advartieing", "would", "be", "miced", "1o", "biack.and-white", "advertisements", "of", "text", "and", "not", "graphics.", "The", "obacco", "\u2018companies", "have", "coniended", "that", "such", "2", "limitason", "would", "inrings", "on", "thelr;", "A", "\u00bb", "woutd", "also", "prectude", "any", "F.D.A.", "role", "In", "en-", "Iorcemen", "of", "tobacco", "regulations.", "And", "unlike", "the", "gencys", "proposal,", "e", "tobacco", "companles'", "proposal", "wold", "ok", "ban", "1abeco", "brandaarae", "spon-", "Sarship", "5", "rodeos", "and", "motor", "3poct.", "2", "Fln", "Meflo.", "&", "scizsworan", "oz", "i", "mer", "tht", "ho", "wolcomed", "3", "Jeiistive", "Solidon", "o", "eemage", "smoking", "s", "PR", "5", "reg.", "3", "\"", "Toe", "Pt", "ora", "roposs", "al", "shorect", "o", "S48", "e", "K.", "Zalerof", "e", "FBA.", "Supporirscl", "e", "tmccanditry,", "\u00a9", "ke", "Reprsencive", "Thoras", ".", "Bl", "5", "Repucanal", "Vi,", "s", "pro", "e", "e", "S", "s", "ot", "beae", "Do", "it", "areacy", "promiaed", "t", "flouiar", "sy", "-", "ek", "el", "precludo", "e", "\u00a9", "PO", "lrom", "sxercuing", "jodeton", "\u00a9", "e", "tbacen\u2019", "i", "A", ":", "oot", "5", "bllon", "worh", "of", "abaces", "|", "il", "noe", "s", "iy", "roduce", "een", "\u2018smoking\u2122", "e", "cied", "a", "study", "shoving", "hat", "more", "an", "T2", "percent", "of", "then-", "\u2018apers", "buy", "clgareted", "in", "convenlence", "tores", "and", "gas", "mations:", "01\u00a39b2p90,"], "bbox": [[129, 442, 141, 468], [128, 406, 140, 437], [128, 368, 140, 401], [127, 323, 140, 363], [125, 249, 140, 317], [125, 215, 136, 243], [125, 199, 139, 211], [124, 174, 136, 194], [177, 88, 279, 96], [177, 113, 200, 145], [210, 107, 344, 157], [359, 107, 460, 157], [476, 107, 543, 157], [547, 111, 868, 153], [790, 107, 863, 157], [221, 161, 237, 171], [241, 161, 290, 170], [294, 161, 354, 170], [190, 176, 237, 186], [242, 177, 257, 185], [261, 175, 327, 184], [332, 177, 344, 184], [350, 175, 397, 185], [177, 187, 238, 198], [242, 187, 254, 196], [258, 187, 277, 195], [282, 186, 330, 195], [334, 187, 346, 195], [351, 187, 397, 196], [177, 200, 213, 207], [221, 198, 275, 206], [282, 197, 314, 208], [322, 199, 343, 206], [350, 198, 397, 207], [177, 210, 241, 220], [246, 208, 301, 219], [307, 209, 367, 219], [372, 209, 397, 217], [176, 220, 232, 240], [237, 220, 269, 230], [273, 219, 328, 230], [327, 219, 397, 240], [383, 209, 403, 244], [212, 232, 222, 240], [269, 230, 319, 241], [327, 220, 340, 248], [356, 230, 396, 241], [176, 242, 224, 252], [228, 242, 258, 250], [262, 241, 285, 250], [290, 241, 354, 251], [358, 241, 396, 250], [176, 253, 236, 262], [240, 253, 261, 261], [265, 253, 336, 263], [190, 264, 212, 272], [216, 264, 236, 272], [240, 264, 305, 274], [310, 265, 339, 271], [346, 263, 396, 272], [176, 275, 190, 286], [198, 274, 245, 284], [251, 274, 265, 283], [271, 274, 330, 285], [348, 275, 354, 283], [362, 273, 396, 283], [176, 287, 202, 295], [218, 276, 286, 312], [294, 276, 342, 312], [344, 285, 396, 294], [184, 297, 218, 306], [294, 298, 314, 308], [364, 297, 385, 305], [184, 308, 204, 317], [209, 308, 222, 317], [225, 308, 299, 317], [267, 298, 278, 326], [286, 298, 297, 326], [303, 307, 396, 317], [176, 321, 187, 328], [190, 320, 218, 328], [222, 321, 273, 329], [277, 319, 331, 329], [335, 319, 359, 327], [364, 321, 396, 327], [171, 320, 332, 348], [336, 320, 400, 348], [176, 342, 194, 350], [198, 341, 265, 351], [270, 341, 322, 351], [326, 342, 339, 349], [344, 342, 351, 349], [355, 341, 396, 351], [176, 352, 228, 361], [233, 353, 265, 360], [188, 363, 210, 371], [214, 364, 237, 371], [241, 362, 305, 373], [309, 365, 322, 369], [326, 362, 363, 372], [367, 362, 395, 371], [175, 374, 192, 383], [200, 374, 238, 383], [246, 373, 265, 382], [271, 373, 319, 382], [326, 373, 350, 381], [358, 373, 368, 381], [376, 373, 396, 381], [176, 384, 212, 395], [220, 384, 261, 393], [270, 384, 339, 395], [348, 384, 368, 392], [376, 385, 396, 392], [175, 396, 208, 404], [214, 396, 257, 404], [262, 395, 316, 405], [324, 395, 367, 404], [374, 394, 396, 403], [175, 407, 193, 415], [197, 407, 229, 415], [241, 407, 277, 415], [281, 406, 331, 415], [335, 405, 396, 416], [175, 418, 193, 427], [204, 417, 251, 427], [262, 418, 305, 428], [316, 418, 372, 428], [384, 417, 396, 425], [205, 429, 224, 439], [230, 429, 277, 437], [285, 428, 306, 436], [314, 428, 344, 436], [351, 431, 364, 434], [371, 430, 396, 438], [173, 505, 205, 514], [201, 494, 273, 522], [279, 510, 359, 512], [216, 517, 222, 526], [230, 515, 271, 523], [279, 515, 301, 523], [310, 514, 348, 523], [358, 514, 395, 523], [173, 516, 221, 544], [229, 516, 251, 544], [257, 516, 311, 544], [319, 527, 323, 534], [330, 516, 351, 544], [356, 516, 370, 544], [375, 516, 400, 544], [173, 537, 358, 557], [287, 533, 301, 567], [314, 533, 342, 567], [351, 537, 395, 557], [168, 591, 196, 619], [202, 601, 393, 613], [266, 591, 302, 619], [310, 591, 326, 619], [331, 591, 370, 619], [375, 591, 397, 619], [187, 625, 218, 633], [226, 623, 275, 632], [285, 625, 291, 631], [320, 623, 368, 631], [376, 623, 393, 631], [173, 635, 209, 645], [216, 635, 259, 644], [269, 621, 311, 655], [315, 634, 335, 643], [172, 645, 269, 654], [277, 644, 298, 653], [306, 644, 342, 652], [383, 644, 392, 653], [173, 647, 213, 666], [217, 655, 242, 664], [246, 655, 265, 664], [270, 655, 334, 665], [340, 655, 377, 663], [381, 656, 393, 663], [172, 668, 205, 676], [230, 666, 295, 677], [305, 666, 322, 675], [330, 667, 372, 676], [381, 667, 393, 674], [172, 678, 209, 686], [216, 679, 238, 688], [244, 677, 290, 686], [297, 677, 343, 687], [350, 677, 379, 686], [385, 678, 392, 685], [173, 688, 257, 698], [262, 690, 275, 697], [282, 688, 327, 696], [334, 688, 380, 696], [389, 689, 393, 696], [172, 699, 242, 708], [246, 698, 315, 707], [319, 698, 356, 707], [362, 698, 393, 709], [172, 695, 209, 729], [214, 695, 234, 729], [241, 710, 253, 718], [257, 709, 316, 718], [187, 721, 208, 729], [240, 720, 286, 728], [291, 719, 347, 728], [352, 719, 372, 728], [168, 731, 206, 740], [210, 730, 392, 740], [282, 716, 309, 749], [319, 730, 392, 740], [172, 742, 234, 752], [238, 741, 275, 751], [269, 736, 274, 758], [279, 741, 298, 749], [302, 741, 331, 750], [336, 741, 358, 749], [363, 741, 392, 750], [172, 753, 262, 762], [267, 751, 324, 760], [330, 753, 343, 760], [348, 753, 392, 762], [172, 764, 204, 772], [210, 749, 277, 782], [283, 764, 286, 771], [309, 749, 320, 782], [342, 763, 368, 771], [377, 749, 392, 782], [172, 774, 208, 783], [228, 775, 240, 782], [246, 774, 265, 782], [271, 776, 309, 784], [315, 773, 339, 782], [346, 774, 392, 782], [172, 785, 236, 795], [240, 784, 275, 793], [279, 784, 392, 792], [338, 770, 346, 803], [356, 770, 368, 803], [377, 770, 397, 803], [180, 795, 226, 817], [232, 795, 315, 816], [172, 808, 179, 817], [184, 818, 206, 825], [212, 817, 225, 825], [229, 817, 238, 825], [244, 816, 299, 827], [305, 816, 355, 824], [360, 816, 392, 824], [171, 830, 201, 838], [236, 828, 254, 836], [262, 828, 301, 836], [307, 828, 316, 835], [324, 827, 392, 835], [172, 838, 221, 848], [236, 838, 311, 849], [326, 838, 392, 847], [172, 850, 206, 858], [213, 850, 259, 858], [265, 850, 322, 857], [328, 850, 343, 856], [350, 849, 392, 858], [435, 175, 462, 185], [469, 173, 541, 186], [433, 192, 494, 204], [501, 192, 608, 206], [415, 215, 417, 232], [435, 207, 469, 221], [477, 208, 553, 222], [435, 227, 489, 238], [493, 229, 546, 238], [550, 227, 616, 238], [435, 237, 493, 248], [497, 239, 571, 250], [435, 286, 457, 297], [461, 287, 523, 298], [529, 287, 590, 298], [594, 287, 612, 296], [435, 298, 484, 307], [489, 299, 549, 307], [435, 310, 525, 321], [529, 310, 602, 320], [433, 525, 469, 534], [473, 525, 506, 536], [511, 525, 546, 534], [550, 526, 603, 536], [433, 537, 469, 548], [473, 537, 515, 548], [521, 539, 530, 546], [535, 537, 564, 546], [571, 537, 606, 546], [432, 549, 454, 558], [458, 549, 496, 558], [500, 551, 533, 558], [537, 549, 563, 558], [432, 561, 481, 572], [485, 561, 546, 570], [550, 561, 611, 571], [433, 573, 444, 581], [448, 573, 497, 583], [502, 572, 541, 581], [546, 572, 579, 581], [412, 582, 413, 602], [432, 584, 481, 594], [485, 585, 529, 593], [555, 584, 590, 593], [412, 603, 413, 606], [432, 598, 496, 607], [500, 596, 538, 607], [543, 598, 557, 605], [562, 598, 611, 607], [432, 608, 444, 617], [448, 608, 462, 616], [466, 608, 502, 619], [507, 609, 514, 617], [519, 599, 547, 627], [553, 599, 586, 627], [412, 629, 632, 639], [412, 652, 470, 660], [477, 651, 489, 660], [496, 651, 514, 660], [521, 651, 570, 660], [578, 651, 632, 659], [412, 663, 464, 673], [474, 663, 518, 673], [530, 664, 541, 671], [551, 662, 631, 671], [412, 674, 631, 685], [477, 665, 531, 693], [537, 665, 559, 693], [563, 665, 574, 693], [579, 665, 620, 693], [411, 687, 466, 697], [472, 687, 549, 696], [553, 688, 586, 697], [594, 687, 631, 696], [411, 699, 441, 706], [448, 699, 458, 706], [466, 698, 500, 706], [505, 699, 531, 706], [538, 698, 562, 706], [568, 698, 586, 706], [594, 698, 631, 706], [411, 708, 432, 718], [441, 710, 485, 720], [494, 711, 505, 718], [513, 709, 527, 718], [535, 709, 561, 718], [570, 709, 631, 720], [412, 722, 453, 730], [425, 733, 446, 741], [462, 733, 498, 741], [503, 733, 543, 740], [549, 733, 572, 741], [578, 733, 596, 741], [602, 734, 631, 741], [412, 745, 450, 755], [461, 746, 490, 753], [501, 744, 567, 754], [576, 745, 588, 752], [599, 743, 631, 752], [412, 757, 442, 764], [448, 756, 503, 766], [509, 756, 580, 764], [587, 756, 631, 763], [805, 90, 830, 98], [653, 161, 685, 170], [701, 162, 713, 170], [720, 161, 758, 169], [763, 160, 775, 169], [782, 160, 801, 169], [806, 160, 852, 169], [859, 159, 874, 168], [880, 167, 883, 169], [653, 172, 693, 182], [700, 172, 724, 180], [730, 171, 755, 180], [762, 171, 797, 180], [805, 172, 822, 180], [830, 172, 874, 181], [653, 183, 681, 191], [688, 182, 744, 193], [750, 182, 805, 192], [811, 182, 847, 191], [854, 182, 883, 191], [880, 173, 887, 201], [653, 194, 720, 213], [728, 195, 741, 202], [749, 194, 770, 202], [778, 193, 816, 202], [824, 193, 846, 202], [855, 192, 874, 201], [667, 205, 709, 213], [714, 205, 745, 213], [749, 204, 785, 213], [789, 204, 802, 213], [807, 203, 872, 213], [653, 215, 690, 224], [700, 216, 718, 224], [728, 215, 774, 224], [783, 216, 836, 224], [844, 214, 874, 224], [653, 226, 687, 235], [690, 226, 758, 236], [762, 225, 814, 234], [802, 215, 812, 243], [820, 224, 874, 234], [864, 215, 877, 243], [653, 236, 749, 245], [759, 236, 852, 245], [862, 236, 874, 244], [653, 249, 676, 256], [683, 248, 704, 257], [712, 249, 730, 256], [737, 248, 791, 258], [798, 247, 820, 256], [827, 247, 874, 255], [653, 259, 717, 269], [721, 259, 750, 267], [754, 258, 814, 267], [818, 248, 843, 276], [848, 248, 874, 276], [653, 271, 660, 278], [667, 270, 725, 278], [730, 269, 766, 278], [773, 269, 819, 279], [824, 271, 839, 278], [844, 269, 876, 281], [653, 280, 775, 300], [777, 293, 783, 302], [838, 291, 872, 301], [653, 303, 677, 311], [683, 304, 709, 313], [740, 304, 762, 312], [767, 302, 805, 310], [811, 302, 834, 311], [839, 302, 850, 310], [855, 303, 874, 310], [652, 314, 714, 322], [725, 314, 737, 322], [746, 314, 793, 322], [803, 313, 875, 323], [647, 314, 675, 342], [680, 314, 716, 342], [721, 314, 737, 342], [745, 314, 793, 342], [797, 323, 876, 334], [863, 314, 883, 342], [652, 335, 698, 343], [705, 335, 773, 345], [781, 334, 831, 345], [839, 333, 874, 343], [652, 347, 672, 354], [679, 346, 700, 354], [708, 345, 754, 354], [775, 346, 835, 353], [842, 346, 874, 354], [653, 356, 697, 366], [701, 356, 713, 364], [717, 356, 757, 364], [762, 346, 785, 374], [787, 357, 824, 364], [828, 356, 866, 365], [647, 356, 663, 390], [652, 367, 697, 386], [704, 366, 744, 375], [750, 368, 758, 375], [765, 367, 848, 375], [856, 366, 874, 385], [863, 378, 866, 385], [652, 444, 677, 451], [684, 442, 706, 451], [712, 442, 726, 450], [732, 442, 793, 450], [798, 444, 806, 450], [811, 441, 872, 452], [651, 453, 698, 462], [704, 455, 716, 462], [721, 455, 771, 463], [777, 452, 827, 463], [834, 452, 858, 461], [652, 466, 705, 483], [714, 475, 724, 483], [728, 476, 748, 485], [820, 480, 823, 483], [659, 472, 669, 504], [664, 486, 696, 494], [701, 485, 737, 496], [744, 486, 783, 493], [790, 485, 840, 495], [846, 484, 872, 493], [651, 496, 726, 504], [705, 483, 717, 515], [730, 495, 802, 505], [806, 495, 855, 504], [859, 495, 872, 504], [652, 507, 702, 516], [708, 507, 726, 516], [730, 506, 769, 516], [664, 519, 671, 527], [754, 518, 765, 526], [769, 517, 872, 527], [881, 519, 883, 521], [652, 529, 673, 538], [714, 529, 769, 538], [773, 528, 831, 537], [827, 516, 835, 548], [847, 527, 872, 539], [652, 540, 671, 550], [675, 540, 758, 550], [763, 540, 832, 550], [823, 526, 838, 558], [848, 540, 872, 549], [651, 550, 750, 570], [754, 550, 803, 559], [809, 552, 814, 558], [824, 551, 872, 560], [667, 562, 705, 572], [729, 548, 773, 584], [779, 561, 846, 580], [850, 561, 872, 569], [652, 573, 676, 581], [712, 574, 724, 582], [773, 573, 785, 580], [803, 572, 844, 581], [850, 573, 872, 582], [881, 575, 884, 577], [651, 572, 713, 593], [751, 582, 786, 591], [794, 582, 846, 592], [852, 582, 872, 590], [880, 582, 884, 592], [651, 594, 689, 603], [697, 594, 726, 602], [733, 594, 797, 604], [802, 593, 872, 604], [881, 596, 884, 599], [651, 606, 675, 613], [684, 591, 734, 623], [748, 604, 755, 612], [762, 604, 790, 612], [881, 603, 884, 605], [664, 615, 700, 624], [705, 615, 718, 624], [725, 615, 761, 624], [767, 614, 802, 623], [807, 614, 820, 623], [826, 614, 871, 623], [881, 620, 884, 623], [649, 712, 687, 720], [693, 701, 709, 729], [717, 712, 726, 719], [781, 701, 793, 729], [799, 701, 840, 729], [848, 701, 877, 729], [649, 722, 693, 731], [721, 722, 734, 730], [737, 712, 769, 740], [773, 723, 778, 730], [786, 712, 815, 740], [822, 721, 871, 732], [649, 733, 675, 741], [681, 735, 713, 741], [720, 733, 745, 741], [753, 733, 765, 740], [771, 732, 835, 743], [823, 722, 834, 750], [842, 733, 872, 740], [644, 733, 681, 761], [687, 733, 709, 761], [714, 742, 871, 754], [779, 733, 793, 761], [798, 742, 871, 754], [644, 745, 685, 773], [690, 745, 713, 773], [718, 745, 737, 773], [742, 754, 793, 764], [893, 817, 917, 899]]}