{"image_dir": "data/RVL_CDIP/images/imagesw/w/y/d/wyd20d00/501110531+-0531.tif", "label": "0", "words": ["CONFIDENTIAL", "May", "26,", "1978", "Mr.", "D.", "J.", "Hopkins", "Re:", "SALEM", "LIGHTS", "June", "26", "Recall", "Test", "This", "confirms", "that", "the", "\"Preferred", "Taste", "-", "Lips\"", "subject", "(revised", "visual/copy", "rendition)", "will", "be", "tested", "in", "place", "of", "\"Champagne", "Glass\u2122", "on", "the", "above", "date.", "Body", "copy,", "which", "makes", "specific", "reference", "to", "women,", "should", "be", "changed", "to", "read", "as", "follows:", "\"Mellow", "flavor,", "cooling", "menthol,", "total", "satisfaction.", "Taste", "why", "SALEM", "LIGHTS", "is", "the", "largest", "selling", "low", "tar", "menthol", "cigarette.\u201d", "This", "subject", "has", "also", "been", "approved", "as", "a", "fourth", "addition", "to", "our", "copy", "pool", "to", "run", "nationally", "concurrent", "with", "testing.", "That", "copy", "pool", "should", "be", "scheduled", "as", "follows", "by", "type", "publication:", "General", "Audience", "Male", "Female", "*", "Lighter", "*", "Profile", "*", "Lips", "*", "Profile", "*", "Map", "*", "Map", "(", ":", "Map", "*", "Lips", "The", "Brand", "should", "review", "final", "art", "before", "the", "\"Lips\u00ae", "subject", "is", "produced.", "B&W", "stats", "for", "formal", "routing", "will", "also", "be", "required", "prior", "to", "closing", "in", "national", "media", "(not", "required", "for", "test).", "Additional", "to", "testing", "of", "\"Lips,\"", "we", "should", "make", "every", "attempt", "to", "have", "an", "MiR", "pick-up", "of", "the", "\"Map\"", "subject", "(recall", "scores", "only)", "at", "the", "same", "time", "that", "results", "are", "reported", "for", "\"Lips", "Recall", "scores", "on", "two", "subjects", "would", "be", "a", "more", "reliable", "indicator", "of", "impact", "levels", "for", "our", "new", "visuals", "than", "having", "results", "on", "only", "one.", "Please", "contact", "Maria", "Falconetti", "regarding", "possible", "pick-up", "issues", "and", "dates.", "If", "you", "have", "any", "questions", "or", "comments,", "please", "don't", "hesitate", "to", "call", "me.", "S.", "C.", "Wooten,", "Jr.", "A.", "MacKinnon", "V.", "McCaffrey", "L.", "Snyder", "C.", "Falconetti", "1e50", "11108", ")"], "bbox": [[343, 24, 602, 60], [493, 71, 526, 84], [541, 70, 570, 82], [587, 69, 629, 81], [104, 135, 135, 145], [149, 135, 168, 145], [183, 134, 201, 145], [217, 133, 295, 147], [241, 181, 271, 190], [298, 180, 355, 190], [367, 179, 435, 189], [448, 179, 493, 189], [507, 178, 527, 189], [541, 178, 608, 188], [622, 179, 667, 188], [106, 226, 149, 237], [161, 226, 250, 237], [265, 225, 309, 237], [322, 225, 354, 236], [370, 225, 482, 236], [494, 225, 550, 235], [564, 229, 572, 230], [587, 223, 641, 237], [657, 223, 736, 237], [753, 222, 839, 236], [106, 241, 228, 255], [241, 240, 351, 253], [367, 240, 412, 251], [425, 240, 446, 251], [461, 240, 527, 251], [542, 239, 563, 250], [575, 240, 632, 252], [644, 239, 667, 250], [681, 239, 793, 252], [106, 257, 169, 268], [184, 260, 205, 268], [218, 257, 250, 268], [263, 256, 320, 267], [332, 256, 387, 267], [413, 256, 458, 269], [472, 258, 525, 269], [541, 255, 598, 266], [610, 255, 667, 265], [680, 254, 770, 268], [107, 273, 205, 284], [218, 274, 240, 283], [251, 274, 318, 284], [334, 271, 401, 282], [413, 271, 436, 282], [449, 271, 527, 284], [541, 271, 563, 281], [576, 270, 620, 281], [633, 273, 655, 281], [669, 270, 755, 280], [152, 304, 229, 314], [242, 303, 318, 315], [334, 302, 412, 315], [425, 302, 514, 314], [530, 301, 584, 312], [599, 300, 745, 312], [163, 320, 217, 330], [229, 319, 263, 332], [275, 319, 332, 329], [344, 318, 413, 329], [427, 317, 446, 328], [461, 318, 494, 329], [507, 318, 586, 331], [599, 316, 677, 330], [693, 316, 725, 327], [163, 335, 194, 345], [206, 334, 286, 345], [299, 333, 423, 346], [106, 373, 149, 384], [163, 373, 240, 386], [253, 373, 286, 383], [299, 372, 344, 382], [356, 372, 401, 382], [415, 371, 505, 384], [518, 374, 539, 382], [553, 374, 563, 381], [576, 371, 645, 381], [657, 370, 749, 381], [761, 370, 782, 380], [794, 372, 828, 380], [107, 392, 151, 402], [163, 389, 205, 402], [218, 389, 240, 399], [253, 391, 286, 398], [299, 387, 413, 401], [427, 388, 539, 398], [553, 386, 598, 397], [611, 386, 700, 399], [726, 385, 771, 396], [783, 388, 828, 398], [106, 404, 149, 418], [163, 404, 229, 415], [241, 403, 263, 414], [277, 403, 379, 414], [392, 406, 413, 414], [427, 403, 505, 413], [518, 402, 541, 416], [554, 403, 598, 415], [611, 400, 746, 415], [173, 434, 251, 445], [263, 433, 356, 444], [496, 432, 541, 443], [657, 431, 725, 442], [176, 465, 183, 471], [196, 465, 275, 478], [486, 464, 493, 469], [507, 463, 587, 474], [660, 463, 667, 468], [681, 462, 725, 476], [176, 480, 183, 486], [196, 480, 275, 491], [486, 479, 493, 484], [507, 479, 541, 491], [660, 478, 667, 483], [680, 479, 714, 491], [9, 490, 18, 510], [176, 496, 183, 501], [196, 497, 229, 509], [176, 511, 183, 517], [197, 511, 240, 525], [108, 551, 140, 561], [152, 550, 208, 561], [220, 549, 287, 560], [301, 548, 368, 559], [381, 548, 437, 559], [450, 549, 484, 558], [496, 548, 563, 558], [578, 548, 611, 558], [625, 547, 690, 560], [705, 547, 783, 560], [797, 546, 818, 557], [107, 565, 204, 578], [230, 565, 265, 575], [278, 565, 332, 574], [347, 564, 380, 574], [393, 563, 461, 573], [474, 562, 553, 576], [564, 562, 610, 573], [624, 562, 669, 573], [681, 562, 704, 572], [717, 561, 806, 575], [108, 581, 163, 594], [175, 581, 196, 591], [208, 579, 287, 593], [302, 579, 322, 590], [335, 579, 425, 590], [437, 578, 496, 589], [513, 578, 553, 591], [566, 577, 657, 591], [671, 577, 704, 588], [717, 577, 782, 590], [107, 611, 218, 622], [232, 612, 253, 621], [266, 610, 344, 623], [358, 610, 380, 621], [395, 609, 470, 623], [485, 612, 507, 620], [521, 609, 588, 620], [599, 609, 645, 619], [659, 611, 716, 621], [728, 609, 806, 621], [819, 609, 842, 619], [107, 627, 151, 637], [164, 629, 185, 637], [197, 627, 232, 637], [242, 625, 323, 638], [335, 625, 356, 636], [371, 625, 404, 636], [417, 624, 470, 638], [486, 624, 564, 638], [582, 623, 657, 636], [671, 626, 738, 634], [750, 623, 803, 637], [819, 624, 840, 634], [108, 642, 140, 653], [153, 644, 196, 652], [209, 641, 253, 652], [266, 641, 311, 652], [324, 641, 403, 651], [417, 643, 449, 651], [462, 640, 554, 653], [567, 640, 599, 650], [614, 638, 669, 652], [717, 639, 783, 649], [797, 641, 863, 649], [108, 660, 129, 668], [141, 658, 175, 668], [187, 656, 277, 670], [289, 656, 346, 667], [358, 656, 380, 667], [393, 658, 404, 666], [416, 658, 461, 666], [474, 655, 564, 666], [579, 654, 681, 665], [693, 654, 716, 665], [729, 654, 795, 667], [809, 654, 875, 665], [110, 673, 140, 683], [152, 675, 185, 683], [197, 675, 230, 683], [242, 672, 322, 682], [336, 672, 380, 682], [393, 671, 461, 684], [474, 671, 553, 682], [566, 674, 588, 681], [600, 670, 647, 683], [659, 673, 701, 680], [729, 670, 795, 680], [809, 670, 887, 680], [107, 688, 163, 699], [176, 687, 287, 698], [302, 686, 404, 700], [417, 686, 507, 700], [521, 686, 600, 699], [614, 685, 681, 696], [694, 685, 728, 696], [740, 685, 805, 696], [110, 719, 128, 730], [141, 722, 175, 733], [187, 719, 230, 729], [244, 721, 277, 732], [290, 718, 392, 731], [405, 720, 427, 728], [440, 718, 539, 729], [555, 717, 623, 730], [636, 715, 693, 727], [706, 715, 795, 727], [809, 717, 831, 727], [108, 735, 151, 745], [164, 737, 193, 745], [533, 802, 551, 812], [567, 802, 586, 812], [602, 802, 680, 813], [694, 801, 725, 811], [244, 836, 262, 846], [278, 834, 381, 845], [244, 851, 263, 860], [278, 849, 381, 863], [244, 866, 263, 876], [279, 865, 347, 878], [244, 881, 263, 891], [279, 880, 393, 891], [887, 900, 899, 934], [884, 844, 896, 887], [657, 903, 688, 929]]}