{"image_dir": "data/RVL_CDIP/images/imagesk/k/o/n/kon68d00/503069037_503069039.tif", "label": "1", "words": ["[", "e", "4.", "HEVIULLS", "TUBAGLY", "LUuneAnT", "Prototype", "Development", "Request", "Date__June", "2,", "1982", "|", "Prolect:", "_MORE", "Lighrs", "100's", "Menthol", "Reference", "Number:", "___82-21506", "'", "Originated", "By:", "o", "I", "Request", "Nome:", "M.", "S.", "Jennings", "_feheckone)", "O3", "Change/Previous", "Reference", "No..", "Department:", "_Brand", "Marketin;", "|1", "QBJECTIVE:", "-", "\u2018", "O3", "New", "Product", "Improve", "product", "vs.", "competition", "as", "determined", "by", "findings", "of", "latest", "O", "Brand", "Extension", "test", "results", "(veport", "dated", "5/26/82)", "and", "revise", "action", "standards.", "(0", "Product", "Modification", "(check", "one)", "[", "n", "RATIONALE:", "{", "-", "Latest", "test", "results", "indicate", "the", "MORE", "Lights", "100's", "Menthol", "has", "been", "|", "rated", "inferior", "to", "competition", "in", "overall", "ratings", "and", "specific", "product", "ateributes.", "-", "Action", "standards", "being", "amended", "to", "include", "franchise", "and", "set", "priorities.", "[", "i", "NDAR", "First", "Priority", " Superiority", "vs.", "Virginia", "Slins", "Lights", "Menthol", "among", "100ma", "FFLT", "menthol", "25-34", "year", "old", "female", "smokers", "(target", "group).", "Second", "Priority", " Superiority", "vs.", "Virginia", "Slims", "Lights", "Menthol", "among", "total", "100mm", "FFLT", "menthol", "female", "smokers.", "E", "{", "Third", "Priority", " Parity", "vs.", "current", "product", "among", "franchise", "smokers", "when", "available", "for", "testing.", "IV.", " COMPETITIVE", "TARGET", "BRANDS:", "Virginia", "Slims", "Lights", "Menthol", "[", "v.", "e", "PECIFICATIONS:", "Max.", "i", "Desired", "Toul", "Length:", "__98.Omm", "Tar", "Delivery:", "9", "_mg/", "8", "_mg/", "9", "_mg.", "per", "cigaretts", "Filtor", "Longth:", "_31-Omm", "Nicotine:", "TBD", "mg/", "__TBD", "mg/", "_TBD", "mg.", "per", "cigarets", "Tipping", "Length:_35-Omm", "Tipping", "Color:", "__Beige", ":", "Circumference:", "22:69mm", "Paper", "Color:", "Beige", "Filter", "Type:", "Standard", "Name", "Placement:", "_Atound", "tipping", "&", "No", "obiection", "(]", "Not", "desired", "V.", " PROPOSED", "TARGET", "DATES:", "ave", "Wave", "1", "10/11/82", "stk", "1", "1276", "Prototypes", "avaaie2e", "1", "B/30/52", "Consumr", "Tests", "(NFO)", "2%", "2", "11/8/82", "inroduction", ")", "yany.", "1oL", "LLLLE:", "Wave", "2", "9/13/82", "laions", "igve", "2", "2/28/8", "VIl", "ESTIMATED", "MARKETING", "OBJECTIVES/COST", "BENEFITS:", "1982", "Unit", "Volume", "Objective", "__2,209", "mm", "1)", " Incremental", "Cost", "Savings", "(Category/Amount):", "Market", "Size", " \u2014", "Units", "635,000", "s", "M", "~", "Share", "Objective", "35", "%", "\u2122M", "'", "Segment", "Size", "\u2014", "Units", "58,864", "_mm", "2)", "\u2122", "!", "-", "Sure", "Obiective", "378", "%", "\u2122", "\u201d", "B", "S", "|", "totAL", "___m", "2", "VIl", "ESTIMATED", "DEVELOPMENT", "COSTS", "(By", "BRAND", "R&D)", "s", ")", "-", "o", "8", "IX.", "Wes", "request", "identified", "a5", "an", "sction", "program", "in", "the", "(3", "Operating", "Plan", "L]", "Revised", "Oper.", "Plan", "[", "Neither.", "\\/", "g", "Requesting", "Department", "Tit", "Signature", "Date", "Anprovls", "Date.", "Brand", "Manager", "R&D", "Marketing", "Director", "wig.", "Director", "RED", "VP", "Mk,", "EVP,", "Mitg.", "APPROVED", "COPIES", "TO:", "Director,", "Bran", "R&D\u2014Dirsctor,", "Quality", "Assurance\u2014Director,", "Prod.", "Planning", "&", "Info,", "Sves.\u2014Comotroliers", "Dapt\u2014Orginator", "RIRT", "Form", "6850", "\u2014", "Aev.", "/81"], "bbox": [[0, 0, 6, 38], [331, 0, 348, 9], [357, 0, 369, 9], [379, 0, 479, 9], [486, 0, 574, 9], [583, 0, 673, 9], [373, 16, 450, 29], [459, 16, 562, 29], [573, 16, 635, 29], [727, 12, 827, 24], [839, 11, 847, 21], [869, 11, 904, 21], [1, 39, 5, 60], [48, 35, 103, 67], [114, 35, 177, 67], [187, 35, 250, 67], [261, 35, 310, 67], [319, 35, 394, 67], [597, 43, 664, 53], [672, 43, 731, 52], [788, 38, 865, 48], [3, 68, 6, 76], [49, 65, 120, 77], [127, 65, 150, 76], [618, 62, 635, 74], [677, 65, 680, 74], [689, 64, 742, 75], [73, 80, 116, 90], [131, 65, 157, 98], [168, 65, 190, 98], [199, 65, 283, 98], [124, 72, 608, 94], [618, 83, 637, 95], [643, 85, 754, 97], [762, 85, 827, 95], [835, 85, 857, 95], [73, 101, 159, 112], [180, 99, 227, 108], [240, 99, 319, 108], [3, 123, 61, 139], [92, 123, 185, 136], [493, 126, 498, 128], [766, 119, 768, 123], [822, 117, 838, 144], [845, 117, 870, 144], [879, 121, 930, 135], [97, 155, 167, 166], [180, 154, 248, 166], [261, 157, 285, 164], [301, 155, 411, 166], [422, 157, 439, 163], [451, 154, 550, 163], [563, 154, 580, 166], [593, 149, 678, 166], [685, 154, 703, 163], [716, 154, 775, 164], [822, 143, 838, 155], [844, 143, 882, 155], [889, 146, 954, 156], [97, 171, 135, 179], [150, 170, 218, 179], [232, 169, 298, 181], [310, 170, 360, 179], [373, 168, 447, 180], [462, 169, 489, 179], [503, 170, 562, 179], [573, 169, 633, 179], [644, 168, 742, 179], [817, 159, 834, 189], [844, 163, 894, 176], [900, 167, 985, 177], [878, 183, 921, 195], [928, 184, 958, 196], [3, 214, 5, 217], [48, 207, 61, 216], [93, 207, 187, 219], [3, 234, 5, 243], [96, 229, 105, 231], [117, 226, 177, 234], [190, 227, 227, 234], [241, 225, 309, 234], [322, 225, 400, 234], [413, 225, 439, 234], [451, 225, 490, 234], [502, 225, 561, 237], [574, 223, 621, 234], [633, 224, 703, 234], [715, 225, 745, 234], [757, 225, 796, 235], [3, 244, 6, 267], [118, 241, 167, 250], [181, 241, 258, 250], [271, 242, 288, 250], [301, 241, 411, 252], [422, 241, 439, 250], [451, 240, 519, 250], [533, 241, 601, 252], [613, 240, 642, 250], [655, 240, 733, 252], [746, 241, 815, 252], [117, 256, 225, 266], [97, 277, 105, 279], [117, 272, 177, 282], [190, 272, 278, 282], [291, 272, 340, 285], [352, 272, 420, 282], [433, 274, 450, 282], [462, 272, 531, 282], [544, 271, 631, 282], [644, 272, 672, 282], [685, 273, 712, 282], [725, 272, 832, 284], [41, 291, 101, 300], [208, 291, 211, 299], [272, 291, 317, 299], [96, 309, 146, 318], [159, 309, 238, 321], [291, 308, 399, 320], [411, 311, 437, 318], [451, 308, 531, 321], [543, 308, 591, 318], [603, 308, 661, 320], [673, 308, 744, 318], [757, 310, 806, 320], [818, 308, 865, 318], [875, 308, 913, 318], [289, 324, 360, 334], [372, 324, 420, 334], [432, 327, 468, 337], [480, 324, 510, 334], [523, 324, 580, 334], [592, 324, 661, 334], [676, 323, 744, 336], [757, 323, 823, 336], [97, 341, 156, 350], [169, 341, 248, 352], [291, 341, 399, 352], [412, 343, 437, 350], [451, 341, 531, 353], [543, 340, 591, 350], [603, 340, 661, 352], [673, 340, 744, 350], [757, 343, 805, 352], [818, 340, 864, 350], [877, 340, 924, 349], [291, 357, 330, 367], [340, 356, 409, 367], [422, 356, 479, 366], [492, 356, 569, 366], [894, 356, 896, 358], [3, 377, 6, 386], [96, 373, 147, 383], [159, 373, 238, 385], [291, 373, 349, 385], [361, 376, 387, 383], [402, 374, 468, 383], [480, 373, 550, 385], [562, 375, 612, 385], [625, 372, 714, 382], [725, 372, 795, 382], [806, 372, 845, 382], [291, 389, 379, 398], [392, 389, 420, 398], [432, 389, 507, 401], [45, 412, 65, 422], [97, 412, 204, 422], [211, 413, 275, 422], [283, 413, 351, 422], [464, 411, 544, 425], [557, 411, 604, 421], [617, 412, 676, 423], [687, 412, 757, 422], [3, 442, 5, 445], [52, 443, 66, 452], [108, 443, 117, 452], [189, 443, 312, 452], [501, 447, 533, 456], [635, 447, 638, 449], [745, 447, 793, 457], [57, 467, 91, 477], [100, 468, 146, 479], [180, 466, 245, 477], [361, 468, 382, 477], [390, 468, 449, 478], [513, 468, 520, 479], [541, 468, 571, 479], [633, 467, 642, 479], [663, 468, 693, 479], [757, 466, 765, 476], [784, 471, 808, 479], [825, 470, 844, 479], [851, 468, 904, 479], [57, 485, 93, 494], [101, 485, 152, 497], [180, 482, 245, 494], [361, 474, 421, 504], [501, 484, 531, 493], [541, 485, 571, 495], [624, 483, 652, 492], [661, 485, 693, 497], [745, 484, 775, 496], [784, 488, 808, 497], [818, 475, 845, 505], [848, 475, 907, 505], [56, 502, 109, 514], [117, 501, 245, 515], [361, 503, 412, 514], [419, 503, 458, 512], [502, 499, 552, 511], [823, 506, 826, 508], [57, 521, 156, 530], [171, 517, 245, 530], [361, 521, 398, 532], [404, 521, 445, 530], [502, 517, 550, 529], [57, 538, 93, 548], [100, 539, 139, 549], [147, 539, 228, 551], [361, 539, 399, 548], [406, 539, 476, 548], [503, 537, 562, 546], [575, 537, 644, 550], [728, 537, 745, 548], [751, 539, 770, 548], [776, 539, 839, 550], [851, 537, 868, 549], [874, 539, 898, 549], [903, 540, 950, 549], [44, 566, 65, 575], [96, 565, 180, 574], [186, 564, 249, 574], [257, 564, 312, 573], [548, 571, 577, 577], [537, 568, 567, 578], [588, 568, 596, 577], [609, 566, 687, 578], [783, 573, 885, 592], [921, 583, 928, 592], [942, 582, 1000, 592], [97, 588, 190, 599], [203, 585, 274, 598], [287, 585, 293, 594], [308, 584, 374, 595], [382, 573, 443, 609], [450, 589, 483, 598], [492, 573, 531, 609], [546, 573, 574, 609], [590, 573, 597, 609], [537, 582, 677, 599], [686, 589, 772, 599], [789, 591, 801, 603], [806, 591, 861, 603], [875, 573, 919, 609], [942, 573, 997, 609], [236, 597, 332, 610], [285, 590, 296, 620], [305, 597, 374, 611], [810, 589, 860, 621], [873, 599, 908, 617], [921, 598, 928, 608], [942, 597, 1000, 609], [39, 614, 65, 623], [99, 614, 189, 623], [195, 613, 289, 623], [297, 612, 437, 623], [443, 612, 523, 622], [135, 634, 173, 644], [186, 635, 215, 644], [221, 635, 272, 644], [279, 626, 345, 653], [353, 626, 428, 653], [441, 636, 463, 643], [481, 633, 497, 645], [522, 633, 599, 643], [608, 633, 637, 643], [643, 633, 691, 645], [704, 633, 842, 645], [97, 654, 144, 663], [152, 654, 178, 663], [201, 658, 210, 660], [221, 654, 254, 663], [357, 647, 426, 659], [703, 652, 711, 662], [844, 652, 855, 661], [202, 676, 211, 678], [220, 671, 255, 680], [263, 671, 325, 682], [399, 667, 425, 677], [439, 670, 451, 680], [830, 670, 856, 681], [2, 690, 5, 697], [97, 690, 156, 701], [163, 690, 189, 699], [201, 695, 211, 696], [221, 690, 255, 699], [368, 685, 425, 697], [441, 691, 464, 698], [481, 686, 497, 698], [844, 688, 855, 697], [2, 700, 5, 719], [202, 713, 211, 715], [220, 708, 257, 717], [263, 708, 325, 718], [389, 704, 425, 714], [441, 707, 451, 716], [842, 706, 855, 716], [959, 717, 972, 724], [422, 728, 425, 731], [960, 725, 973, 732], [2, 747, 5, 757], [622, 738, 674, 747], [727, 738, 856, 748], [962, 735, 976, 750], [33, 758, 66, 767], [99, 757, 189, 767], [197, 757, 313, 766], [319, 756, 368, 766], [381, 757, 403, 768], [412, 757, 464, 766], [473, 756, 511, 766], [582, 756, 590, 766], [745, 756, 755, 765], [964, 753, 977, 759], [967, 771, 980, 778], [969, 780, 981, 787], [46, 794, 66, 803], [97, 794, 124, 803], [131, 795, 180, 804], [187, 794, 249, 803], [257, 796, 268, 803], [275, 796, 289, 803], [296, 795, 338, 803], [344, 796, 399, 805], [406, 793, 417, 802], [424, 793, 443, 802], [455, 780, 476, 810], [484, 790, 550, 804], [557, 793, 583, 802], [601, 780, 620, 810], [625, 790, 676, 802], [682, 793, 719, 804], [727, 793, 754, 802], [766, 791, 776, 803], [788, 791, 842, 803], [896, 767, 916, 801], [971, 791, 985, 805], [216, 814, 268, 827], [281, 814, 374, 827], [52, 824, 88, 854], [275, 824, 351, 854], [494, 824, 536, 853], [718, 823, 802, 853], [942, 831, 979, 842], [46, 851, 96, 861], [108, 852, 178, 863], [637, 852, 680, 861], [46, 872, 127, 881], [150, 872, 229, 881], [648, 873, 676, 884], [46, 893, 127, 902], [140, 892, 169, 901], [608, 895, 627, 904], [640, 894, 674, 905], [600, 916, 634, 927], [640, 917, 678, 928], [24, 961, 100, 969], [105, 962, 154, 970], [160, 962, 178, 970], [194, 962, 245, 971], [251, 963, 285, 970], [291, 963, 383, 972], [389, 963, 432, 971], [438, 963, 560, 971], [566, 962, 596, 970], [603, 962, 652, 971], [657, 962, 667, 970], [673, 962, 702, 970], [707, 962, 825, 970], [830, 962, 930, 971], [24, 978, 58, 986], [65, 979, 96, 986], [103, 979, 143, 987], [150, 983, 157, 985], [165, 980, 186, 986], [197, 980, 221, 987]]}