{"image_dir": "data/RVL_CDIP/images/imagesb/b/n/g/bng72f00/tob10434.97.tif", "label": "4", "words": [":", "o", ":", "SAO", "PAULO", "o", "A", "1A+", "L8", "MOELES", "W", "YORK:", "PITSHURGH:WASHIGTON", "TCPNTO", "SOUTH", "AR", "310", "e", "o0", "G", "STTGAT", "A", "G", "K.", "SMAPORE", "TONTO.", "AL", "LAEUR", "Marsteller", "Inc.", "ADVERTISING", "+", ":", "ADVERTISING", "COPY", "CLIENT", "TOBACCO", "INSTITUTE", "SPACE", "N", "JoBNUMBER", "43135", "PUBLICATION.", "bare", "14", "December", "1981", "1SSUE", "FLAG:", "ANSWERS", "TO", "THE", "MOST", "ASKED", "QUESTIONS", "ABOUT", "CIGARETTES.", ".", "HEADLINE:", "QUESTION", "3", "3", "DOES", "CIGARETTE", "ADVERTISING", "CAUSE", "KIDS", "TO", "START", "SMOKING?", "COPY", ":", "\"Advertising", "certainly", "is", "not", "the", "culprit.\u201d", "That's", "how", "a", "-", "Director", "of", "the", "U.S.", "Office", "on", "Smoking", "&", "Health", "answered", "the", "-", ".", "question.", "If", "advertising", "doesn't", "cause", "kids", "to", "smoke,", "what", "does?", "There", "are", "no", "pat", "answers.", "Research", "by", "experts", "indicates", "peer", "pressure", "is", "important,", "as", "well", "as", "many", "other", "complex", "psycholog-", "ical,", "cultural,", "and", "socioeconomic", "factors.", "There", "may", "be", "as", "many", "reasons", "why", "as", "there", "are", "kids", "who", "do.", "While", "cigarette", "industry", "sales", "are", "increasing,", "fewer", "teenagers", "are", "smoking.", "For", "example,", "the", "American", "Cancer", "Society", "reports", "that", "among", "young", "women,", "smoking", "has", "decreased", "17", "percent", "since", "We", "think", "that's", "good", "because", "we", "don't", "think", "kids", "should", "smoke.", "Smoking", "is", "an", "adult", "custom", "based", "on", "mature", "and", "informed", "judg-", "ment.", "That's", "right,", "adults,", "not", "children.", "If", "you'd", "like", "more", "information,", "write", "for", "our", "booklet,", "\"Answers", "to", "t", "h", "o", "most", "asked", "questions", "about", "cigarettes.\"", "Address:", "The", "Tobacco", "Institute,", "P.O.", "Box", "1875,", "Washington,", "D.C.", "20006.", "We", "offer", "it", "in", "the", "belief", "that", "full", "and", "free", "discussion", "of", "these", "important", "public", "issues", "is", "in", "the", "public", "interest.", "And", "that", "in", "matters", "of", "adult", "social", "customs,", "the", "vast", "majority", "of", "fair-minded", "Americans", "honor", "individual", "freedom", "of", "choice.", "TAG:", "Weigh", "both", "sides", "before", "you", "take", "sides.", "ety", "7.", "WooRE", "CONFIDENTIAL:", "TIMN", "0247364", "G.", "STUNZ", "MINNESOTA", "TOBACCO", "LITIGATION"], "bbox": [[53, 47, 58, 52], [585, 56, 589, 59], [753, 54, 755, 56], [762, 45, 783, 67], [786, 51, 824, 59], [106, 59, 132, 66], [170, 59, 201, 66], [212, 38, 262, 74], [269, 57, 288, 64], [300, 38, 347, 74], [365, 56, 380, 64], [388, 38, 422, 74], [426, 53, 583, 66], [591, 53, 647, 61], [662, 38, 697, 74], [704, 38, 743, 74], [762, 38, 783, 74], [48, 65, 549, 77], [386, 49, 436, 85], [451, 49, 466, 85], [486, 49, 550, 85], [562, 65, 577, 72], [608, 65, 623, 72], [634, 65, 669, 72], [676, 49, 737, 85], [749, 49, 791, 85], [806, 63, 829, 70], [840, 63, 886, 71], [353, 142, 577, 165], [522, 138, 582, 173], [10, 206, 137, 217], [145, 210, 147, 216], [211, 211, 212, 214], [382, 212, 505, 224], [512, 212, 558, 223], [11, 239, 67, 248], [137, 236, 218, 247], [232, 236, 335, 246], [445, 237, 491, 246], [678, 246, 681, 250], [11, 256, 109, 265], [138, 251, 194, 262], [445, 253, 548, 262], [12, 255, 53, 288], [132, 266, 152, 277], [161, 267, 253, 278], [268, 266, 311, 277], [445, 270, 487, 279], [10, 327, 63, 339], [137, 328, 217, 338], [230, 328, 254, 338], [265, 327, 300, 338], [314, 327, 358, 337], [372, 327, 430, 337], [441, 325, 545, 338], [559, 325, 617, 336], [629, 324, 753, 339], [900, 336, 907, 340], [10, 359, 109, 369], [137, 358, 229, 371], [243, 359, 251, 369], [741, 366, 744, 368], [138, 374, 183, 384], [197, 373, 300, 384], [314, 372, 441, 383], [454, 372, 510, 382], [524, 371, 568, 382], [582, 371, 605, 381], [618, 371, 675, 381], [688, 370, 781, 381], [10, 405, 52, 415], [61, 407, 63, 415], [138, 403, 277, 414], [291, 403, 393, 415], [408, 403, 428, 413], [442, 403, 474, 413], [489, 402, 521, 412], [536, 401, 638, 414], [664, 401, 732, 412], [746, 401, 781, 411], [795, 403, 805, 411], [29, 426, 31, 428], [138, 419, 230, 429], [243, 418, 264, 428], [278, 418, 311, 428], [325, 418, 367, 428], [384, 417, 451, 428], [465, 420, 486, 427], [501, 417, 581, 429], [594, 417, 605, 426], [617, 416, 687, 426], [701, 415, 792, 426], [805, 415, 838, 425], [947, 419, 954, 421], [24, 440, 26, 443], [138, 433, 237, 447], [139, 465, 159, 475], [174, 464, 300, 476], [314, 464, 393, 474], [408, 466, 464, 474], [477, 463, 521, 473], [535, 463, 557, 472], [571, 462, 637, 475], [652, 462, 697, 472], [712, 461, 768, 471], [137, 494, 194, 505], [208, 496, 241, 504], [255, 496, 277, 504], [290, 494, 323, 506], [338, 495, 424, 503], [454, 492, 545, 502], [558, 492, 580, 504], [594, 491, 674, 504], [689, 491, 791, 501], [805, 492, 851, 502], [138, 511, 229, 521], [244, 508, 264, 518], [279, 508, 390, 520], [408, 510, 428, 517], [441, 507, 486, 517], [501, 510, 521, 517], [535, 509, 580, 519], [594, 506, 651, 516], [665, 506, 744, 518], [758, 505, 874, 517], [139, 523, 190, 536], [208, 522, 309, 534], [325, 522, 358, 532], [372, 521, 522, 532], [536, 521, 624, 531], [652, 520, 708, 530], [722, 522, 755, 532], [769, 520, 792, 530], [806, 521, 826, 529], [137, 541, 183, 550], [197, 540, 276, 548], [288, 537, 323, 549], [337, 540, 358, 547], [372, 537, 428, 547], [442, 539, 474, 546], [488, 536, 533, 546], [547, 536, 581, 545], [595, 536, 624, 545], [133, 566, 189, 579], [203, 569, 306, 585], [321, 569, 412, 582], [426, 570, 482, 580], [497, 573, 529, 580], [543, 570, 666, 583], [684, 571, 740, 581], [753, 572, 856, 583], [133, 586, 166, 593], [180, 583, 267, 596], [296, 584, 329, 594], [343, 584, 432, 597], [449, 584, 482, 595], [496, 585, 586, 595], [601, 585, 669, 595], [681, 586, 762, 598], [777, 586, 856, 598], [133, 598, 176, 623], [192, 601, 248, 611], [260, 601, 318, 611], [330, 601, 396, 612], [413, 599, 493, 612], [507, 600, 539, 610], [554, 600, 657, 610], [671, 600, 692, 610], [704, 601, 784, 613], [800, 601, 856, 611], [132, 642, 153, 652], [167, 642, 222, 659], [234, 642, 305, 659], [319, 643, 363, 655], [377, 643, 458, 654], [470, 646, 493, 654], [507, 644, 562, 654], [576, 644, 633, 654], [646, 644, 690, 655], [704, 645, 773, 655], [787, 645, 852, 656], [133, 657, 212, 670], [226, 660, 246, 667], [262, 660, 281, 667], [296, 658, 351, 668], [366, 659, 435, 668], [446, 658, 505, 669], [517, 662, 538, 669], [552, 660, 620, 669], [634, 660, 667, 670], [681, 659, 773, 670], [786, 660, 843, 672], [132, 672, 184, 682], [213, 672, 281, 683], [296, 672, 361, 685], [377, 673, 454, 686], [470, 674, 502, 684], [519, 674, 618, 684], [133, 707, 152, 717], [166, 708, 222, 720], [237, 708, 281, 718], [295, 710, 339, 718], [354, 708, 488, 720], [503, 708, 562, 718], [577, 708, 609, 718], [623, 710, 656, 718], [669, 708, 758, 720], [776, 708, 866, 718], [132, 723, 152, 732], [166, 724, 175, 733], [190, 723, 199, 733], [213, 726, 222, 733], [248, 723, 292, 733], [307, 723, 363, 733], [376, 722, 479, 735], [493, 723, 548, 733], [563, 722, 687, 735], [729, 723, 816, 733], [131, 737, 164, 747], [176, 737, 256, 748], [272, 737, 384, 750], [399, 737, 441, 747], [458, 737, 491, 747], [506, 737, 558, 749], [575, 737, 698, 749], [715, 738, 756, 748], [774, 737, 839, 747], [131, 766, 152, 776], [166, 766, 222, 776], [237, 766, 256, 776], [273, 766, 292, 776], [307, 759, 339, 776], [352, 766, 421, 776], [436, 765, 478, 775], [494, 765, 536, 775], [552, 765, 585, 775], [600, 766, 643, 775], [659, 765, 772, 776], [791, 765, 811, 775], [136, 781, 192, 791], [206, 781, 307, 793], [321, 781, 390, 793], [404, 781, 472, 791], [487, 784, 506, 791], [521, 781, 541, 791], [555, 781, 589, 791], [603, 781, 670, 792], [684, 781, 783, 791], [131, 809, 164, 820], [178, 809, 221, 819], [237, 809, 256, 819], [270, 810, 351, 820], [365, 810, 385, 820], [402, 809, 454, 819], [469, 809, 536, 819], [552, 810, 639, 821], [657, 809, 689, 819], [703, 810, 748, 819], [762, 809, 853, 821], [131, 825, 151, 835], [166, 824, 292, 835], [306, 825, 409, 835], [423, 824, 479, 834], [494, 823, 608, 834], [623, 824, 702, 835], [715, 824, 736, 834], [751, 823, 828, 834], [2, 868, 43, 878], [129, 869, 187, 881], [199, 869, 244, 878], [258, 869, 314, 879], [328, 869, 396, 879], [410, 871, 442, 881], [458, 868, 502, 878], [516, 868, 580, 878], [1, 889, 21, 910], [187, 930, 204, 939], [221, 930, 278, 940], [445, 910, 617, 944], [759, 911, 839, 932], [848, 918, 950, 941], [187, 944, 204, 954], [221, 945, 278, 954], [338, 943, 470, 956], [477, 942, 585, 955], [592, 942, 723, 954]]}